MANIFEST.in
README.rst
TITLE.txt
lh-agpl3-LICENSE.txt
setup.py
./bin/bashIcmSelfcontainedExample.sh
./bin/bashIcmStandaloneExample.sh
./bin/icmBxoExamples.py
bisos2/__init__.py
bisos2.examples.egg-info/PKG-INFO
bisos2.examples.egg-info/SOURCES.txt
bisos2.examples.egg-info/dependency_links.txt
bisos2.examples.egg-info/namespace_packages.txt
bisos2.examples.egg-info/not-zip-safe
bisos2.examples.egg-info/requires.txt
bisos2.examples.egg-info/top_level.txt
bisos2/examples/__init__.py
bisos2/examples/icmLibBegin.py
bisos2/examples/icmLibPkgBegin.py